idmhelpers/__init__.py
idmhelpers/credentials.py
idmhelpers/dlthelper.py
idmhelpers/githelper.py
idmhelpers/partition.py
idmhelpers-0.2.11.dist-info/WHEEL
idmhelpers-0.2.11.dist-info/METADATA
idmhelpers-0.2.11.dist-info/RECORD
