Metadata-Version: 2.1
Name: idmhelpers
Version: 0.2.11
Summary: Helper library for common Databricks activities for Data Engineering, Delta Tables, Pipelines
Author: divyavanmahajan
Author-email: divya.mahajan@outlook.com
Classifier: Programming Language :: Python :: 2
Classifier: Programming Language :: Python :: 2.7
Classifier: Programming Language :: Python :: 3
Classifier: Programming Language :: Python :: 3.10
Classifier: Programming Language :: Python :: 3.4
Classifier: Programming Language :: Python :: 3.5
Classifier: Programming Language :: Python :: 3.6
Classifier: Programming Language :: Python :: 3.7
Classifier: Programming Language :: Python :: 3.8
Classifier: Programming Language :: Python :: 3.9
